aacrepair/__init__.py
aacrepair/audio_conf.py
aacrepair/cmd.py
aacrepair/crc.py
aacrepair/header_aac.py
aacrepair/Test/test__init__.py
aacrepair/Test/aac_file/empty.aac
aacrepair/Test/aac_file/near_empty.aac
aacrepair/Test/aac_file/noAac.mp14
aacrepair/Test/aac_file/white_noise.aac
aacRepair-0.7.dist-info/LICENSE.rst
aacRepair-0.7.dist-info/METADATA
aacRepair-0.7.dist-info/WHEEL
aacRepair-0.7.dist-info/entry_points.txt
aacRepair-0.7.dist-info/top_level.txt
aacRepair-0.7.dist-info/zip-safe
aacRepair-0.7.dist-info/RECORD
