Metadata-Version: 2.1
Name: aacRepair
Version: 0.7
Summary: repair aac files
Author: René Horn
Author-email: rene_horn@gmx.net
License: MIT License
Project-URL: homepage, https://github.com/44xtc44
Project-URL: documentation, https://aacRepair.readthedocs.io/
Project-URL: repository, https://github.com/44xtc44/aacRepair
Keywords: aac repair,aacp repair,aac file repair,aacp file repair
Classifier: Programming Language :: Python :: 3
Classifier: License :: OSI Approved :: MIT License
Classifier: Operating System :: Microsoft :: Windows
Classifier: Operating System :: OS Independent
Classifier: Operating System :: POSIX :: Linux
Classifier: Operating System :: Android
Classifier: Development Status :: 5 - Production/Stable
Classifier: Topic :: Multimedia :: Sound/Audio :: Capture/Recording
Requires-Python: >=3.6
License-File: LICENSE.rst
Provides-Extra: testing
Requires-Dist: pytest (>=6.0) ; extra == 'testing'
Requires-Dist: pytest-cov (>=2.0) ; extra == 'testing'
Requires-Dist: mypy (>=0.9.10) ; extra == 'testing'
Requires-Dist: flake8 (>=3.9) ; extra == 'testing'
Requires-Dist: tox (>=3.24) ; extra == 'testing'
